LICENSE.txt
MANIFEST.in
README.md
requirements.txt
setup.cfg
setup.py
snpaas_cli/__init__.py
snpaas_cli/snpaas.py
snpaas_cli.egg-info/PKG-INFO
snpaas_cli.egg-info/SOURCES.txt
snpaas_cli.egg-info/dependency_links.txt
snpaas_cli.egg-info/entry_points.txt
snpaas_cli.egg-info/top_level.txt