Metadata-Version: 1.1
Name: snpaas-cli
Version: 0.1.4
Summary: Manage SNPaaS
Home-page: https://github.com/springernature/ee-snpaas-cli
Author: Jose Riguera Lopez
Author-email: jose.riguera@springernature.com
License: MIT
Download-URL: https://github.com/springernature/ee-snpaas-cli/releases/tag/v0.1.4
Keywords: snpaas cf bosh credhub manage deployments
Platform: UNKNOWN
Classifier: Development Status :: 5 - Production/Stable
Classifier: Intended Audience :: System Administrators
Classifier: Topic :: System :: Systems Administration
Classifier: License :: OSI Approved :: MIT License
Classifier: Programming Language :: Python :: 2.7
Classifier: Programming Language :: Python :: 3
